ce_machine_learning/__init__.py
ce_machine_learning/client.py
ce_machine_learning/requirements.txt
ce_machine_learning/gen/__init__.py
ce_machine_learning/gen/ce_machine_learning_pb2.py
ce_machine_learning/gen/ce_machine_learning_pb2_grpc.py
ce_machine_learning/gen/model.py
ce_machine_learning-0.0.2.dist-info/METADATA
ce_machine_learning-0.0.2.dist-info/WHEEL
ce_machine_learning-0.0.2.dist-info/top_level.txt
ce_machine_learning-0.0.2.dist-info/RECORD
