Metadata-Version: 2.1
Name: ce-machine-learning
Version: 0.0.2
Summary: Python client for Machine Learning features of Crédito Express
Home-page: UNKNOWN
Author: Crédito Express
Author-email: contato@creditoexpress.com.br
License: UNKNOWN
Platform: UNKNOWN
Requires-Dist: grpcio (>=1.43.0)
Requires-Dist: pydantic (>=1.9.0)
Requires-Dist: protobuf (>=3.19.3)
